lib_cells.v
// lib_cells.v
//-----------------------------------------------------------------------------
//  Behavioral stubs for your standard cells, so Icarus can elaborate net1.v
//-----------------------------------------------------------------------------

module SDFFRX1 (
    input  D,
    input  SE,
    input  SI,
    input  CK,
    input RN,
    output Q,
    output QN
);
  reg state;
  always @(posedge CK or negedge RN) begin
    if (!RN) state <= 1'b0;
    else if (SE) state <= SI;
    else state <= D;
  end
  assign Q  = state;
  assign QN = ~state;
endmodule

module DFFRX1 (
    input D,
    input CK,
    input RN,
    output reg Q,
    output QN
);
  always @(posedge CK or negedge RN) begin
    if (!RN) Q <= 1'b0;
    else Q <= D;
  end
  assign QN = ~Q;
endmodule

module NAND2XL (
    input  A,
    input  B,
    output Y
);
  assign Y = ~(A & B);
endmodule

module AND2XL (
    input  A,
    input  B,
    output Y
);
  assign Y = A & B;
endmodule

module OAI2BB2XL (
    input  A0N,
    input  A1N,
    input  B0,
    input  B1,
    output Y
);
  // Y = ~((~(A0N & A1N)) & (B0 & B1))
  assign Y = ~((~(A0N & A1N)) & (B0 | B1));
endmodule

module AOI2BB1XL (
    input  A0N,
    input  A1N,
    input  B0,
    output Y
);
  // Y = ~((~(A0N | A1N)) | B0)
  assign Y = ~((~(A0N | A1N)) | B0);
endmodule

module CLKINVX1 (
    input  A,
    output Y
);
  assign Y = ~A;
endmodule


module AOI21XL (
    input A0,
    input A1,
    input B0,
    output Y
);
    assign Y = ~(B0 | (A0 & A1));
endmodule

module XOR2XL (
    input A,
    input B,
    output Y
);
    assign Y = A ^ B;
endmodule

simple_counter.v
module simple_counter(clk, reset, en, in, out);
    input clk, reset, en;
    input [3:0] in;
    output [3:0] out;

    // Simple 4-bit up counter logic
    // D[0] = Q[0] ^ 1 (toggle LSB)
    // D[1] = Q[1] ^ (Q[0] & 1) (toggle if LSB was 1)
    // D[2] = Q[2] ^ (Q[1] & Q[0] & 1) (toggle if both lower bits were 1)
    // D[3] = Q[3] ^ (Q[2] & Q[1] & Q[0] & 1) (toggle if all lower bits were 1)

    // Internal nets
    wire n_0, n_1, n_2, n_3, n_4, n_5, n_6, n_7, n_8, n_9, n_10, n_11;

    // Reset signal (active low)
    CLKINVX1 g0 (.A(reset), .Y(n_0));

    // D[0] = Q[0] ^ 1 = ~Q[0]
    CLKINVX1 g1 (.A(out[0]), .Y(n_1));
    assign n_2 = n_1;  // D[0]

    // D[1] = Q[1] ^ (Q[0] & 1) = Q[1] ^ Q[0]
    XOR2XL g2 (.A(out[1]), .B(out[0]), .Y(n_3));
    assign n_4 = n_3;  // D[1]

    // D[2] = Q[2] ^ (Q[1] & Q[0])
    AND2XL g3 (.A(out[1]), .B(out[0]), .Y(n_5));
    XOR2XL g4 (.A(out[2]), .B(n_5), .Y(n_6));
    assign n_7 = n_6;  // D[2]

    // D[3] = Q[3] ^ (Q[2] & Q[1] & Q[0])
    AND2XL g5 (.A(out[2]), .B(out[1]), .Y(n_8));
    AND2XL g6 (.A(n_8), .B(out[0]), .Y(n_9));
    XOR2XL g7 (.A(out[3]), .B(n_9), .Y(n_10));
    assign n_11 = n_10;  // D[3]

    // Flip-flops
    SDFFRX1 count_reg_3 (.D(n_11), .SE(en), .SI(in[3]), .CK(clk), .RN(n_0), .Q(out[3]), .QN());
    SDFFRX1 count_reg_2 (.D(n_7), .SE(en), .SI(in[2]), .CK(clk), .RN(n_0), .Q(out[2]), .QN());
    SDFFRX1 count_reg_1 (.D(n_4), .SE(en), .SI(in[1]), .CK(clk), .RN(n_0), .Q(out[1]), .QN());
    DFFRX1 count_reg_0 (.D(n_2), .CK(clk), .RN(n_0), .Q(out[0]), .QN());

endmodule

module top(clk, reset, en, in, out);
    input clk, reset, en;
    input [3:0] in;
    output [3:0] out;

    simple_counter counter_inst (
        .clk(clk),
        .reset(reset),
        .en(en),
        .in(in),
        .out(out)
    );

endmodule

testbench.v
`timescale 1ns/1ps

module tb;
  // width of your scan chain
  localparam N = 4;

  // Testbench signals
  reg         clk    = 0;
  reg         reset;       // no default here
  reg         en     = 1;
  reg  [N-1:0] in    = 0;
  wire [N-1:0] out;


  initial begin
    $dumpfile("wave.vcd");
    $dumpvars(0, tb);
  end



  // Clock generator: 10 ns period
  always #5 clk = ~clk;

  //-------------------------------------------------------------------------
  // DUT instantiation
  //-------------------------------------------------------------------------
  top u_dut (
    .clk   (clk),
    .reset (reset),   // drives RN in your SDFFRX1 cells
    .en    (en),
    .in    (in),
    .out   (out)
  );

  //-------------------------------------------------------------------------
  // Reset & VCD dump
  //-------------------------------------------------------------------------
  initial begin
    // assert reset (active-low RN) for two cycles
    reset = 1;       
    #1;              // ensure reset=1 at time=0+δ
    @(posedge clk);  // cycle 1
    //@(posedge clk);  // cycle 2
    reset = 0;       // de-assert reset (RN=0 → normal operation)

  end

endmodule

wave.vcd
$date
	Fri Jun 27 16:08:38 2025
$end
$version
	Icarus Verilog
$end
$timescale
	1ps
$end
$scope module tb $end
$var wire 4 ! out [3:0] $end
$var reg 1 " clk $end
$var reg 1 # en $end
$var reg 4 $ in [3:0] $end
$var reg 1 % reset $end
$scope module u_dut $end
$var wire 1 " clk $end
$var wire 1 # en $end
$var wire 4 & in [3:0] $end
$var wire 1 % reset $end
$var wire 4 ' out [3:0] $end
$scope module counter_inst $end
$var wire 1 " clk $end
$var wire 1 # en $end
$var wire 4 ( in [3:0] $end
$var wire 1 ) n_11 $end
$var wire 1 * n_2 $end
$var wire 1 + n_4 $end
$var wire 1 , n_7 $end
$var wire 1 % reset $end
$var wire 4 - out [3:0] $end
$var wire 1 . n_9 $end
$var wire 1 / n_8 $end
$var wire 1 0 n_6 $end
$var wire 1 1 n_5 $end
$var wire 1 2 n_3 $end
$var wire 1 3 n_10 $end
$var wire 1 4 n_1 $end
$var wire 1 5 n_0 $end
$scope module count_reg_0 $end
$var wire 1 " CK $end
$var wire 1 * D $end
$var wire 1 6 QN $end
$var wire 1 5 RN $end
$var reg 1 7 Q $end
$upscope $end
$scope module count_reg_1 $end
$var wire 1 " CK $end
$var wire 1 + D $end
$var wire 1 8 Q $end
$var wire 1 9 QN $end
$var wire 1 # SE $end
$var wire 1 : SI $end
$var wire 1 5 RN $end
$var reg 1 ; state $end
$upscope $end
$scope module count_reg_2 $end
$var wire 1 " CK $end
$var wire 1 , D $end
$var wire 1 < Q $end
$var wire 1 = QN $end
$var wire 1 # SE $end
$var wire 1 > SI $end
$var wire 1 5 RN $end
$var reg 1 ? state $end
$upscope $end
$scope module count_reg_3 $end
$var wire 1 " CK $end
$var wire 1 ) D $end
$var wire 1 @ Q $end
$var wire 1 A QN $end
$var wire 1 # SE $end
$var wire 1 B SI $end
$var wire 1 5 RN $end
$var reg 1 C state $end
$upscope $end
$scope module g0 $end
$var wire 1 % A $end
$var wire 1 5 Y $end
$upscope $end
$scope module g1 $end
$var wire 1 D A $end
$var wire 1 4 Y $end
$upscope $end
$scope module g2 $end
$var wire 1 E A $end
$var wire 1 F B $end
$var wire 1 2 Y $end
$upscope $end
$scope module g3 $end
$var wire 1 G A $end
$var wire 1 H B $end
$var wire 1 1 Y $end
$upscope $end
$scope module g4 $end
$var wire 1 I A $end
$var wire 1 1 B $end
$var wire 1 0 Y $end
$upscope $end
$scope module g5 $end
$var wire 1 J A $end
$var wire 1 K B $end
$var wire 1 / Y $end
$upscope $end
$scope module g6 $end
$var wire 1 / A $end
$var wire 1 L B $end
$var wire 1 . Y $end
$upscope $end
$scope module g7 $end
$var wire 1 M A $end
$var wire 1 . B $end
$var wire 1 3 Y $end
$upscope $end
$upscope $end
$upscope $end
$upscope $end
$enddefinitions $end
#0
$dumpvars
0M
0L
0K
0J
0I
0H
0G
0F
0E
0D
0C
0B
1A
0@
0?
0>
1=
0<
0;
0:
19
08
07
16
05
14
03
02
01
00
0/
0.
b0 -
0,
0+
1*
0)
b0 (
b0 '
b0 &
1%
b0 $
0#
1"
b0 !
$end
#5000
0"
#10000
15
0%
1"
#15000
0"
#20000
1+
12
0*
04
06
1L
1H
1F
1D
b1 !
b1 '
b1 -
17
1"
#25000
0"
#30000
1*
14
16
0L
0H
0F
0D
09
1K
1G
1E
07
b10 !
b10 '
b10 -
18
1;
1"
#35000
0"
#40000
1,
10
11
0+
02
0*
04
06
1L
1H
1F
1D
b11 !
b11 '
b11 -
17
1"
#45000
0"
#50000
1*
14
01
1,
10
16
0L
0H
0F
0D
19
0K
0G
0E
0=
1J
1I
07
08
0;
b100 !
b100 '
b100 -
1<
1?
1"
#55000
0"
#60000
1+
12
0*
04
06
1L
1H
1F
1D
b101 !
b101 '
b101 -
17
1"
#65000
0"
#70000
1*
14
1/
16
0L
0H
0F
0D
09
1K
1G
1E
07
b110 !
b110 '
b110 -
18
1;
1"
#75000
0"
#80000
1)
13
0,
00
1.
11
0+
02
0*
04
06
1L
1H
1F
1D
b111 !
b111 '
b111 -
17
1"
#85000
0"
#90000
0.
1*
14
01
0/
0,
00
1)
13
16
0L
0H
0F
0D
19
0K
0G
0E
1=
0J
0I
0A
1M
07
08
0;
0<
0?
b1000 !
b1000 '
b1000 -
1@
1C
1"
#95000
0"
#100000
1+
12
0*
04
06
1L
1H
1F
1D
b1001 !
b1001 '
b1001 -
17
1"
#105000
0"
#110000
1*
14
16
0L
0H
0F
0D
09
1K
1G
1E
07
b1010 !
b1010 '
b1010 -
18
1;
1"
#115000
0"
#120000
1,
10
11
0+
02
0*
04
06
1L
1H
1F
1D
b1011 !
b1011 '
b1011 -
17
1"
#125000
0"
#130000
1*
14
01
1,
10
16
0L
0H
0F
0D
19
0K
0G
0E
0=
1J
1I
07
08
0;
b1100 !
b1100 '
b1100 -
1<
1?
1"
#135000
0"
#140000
1+
12
0*
04
06
1L
1H
1F
1D
b1101 !
b1101 '
b1101 -
17
1"
#145000
0"
#150000
1*
14
1/
16
0L
0H
0F
0D
09
1K
1G
1E
07
b1110 !
b1110 '
b1110 -
18
1;
1"
#155000
0"
#160000
0)
03
0,
00
1.
11
0+
02
0*
04
06
1L
1H
1F
1D
b1111 !
b1111 '
b1111 -
17
1"
#165000
0"
#170000
0.
1*
14
01
0/
0,
00
0)
03
16
0L
0H
0F
0D
19
0K
0G
0E
1=
0J
0I
1A
0M
07
08
0;
0<
0?
b0 !
b0 '
b0 -
0@
0C
1"
#175000
0"
#180000
1+
12
0*
04
06
1L
1H
1F
1D
b1 !
b1 '
b1 -
17
1"
#185000
0"
#190000
1*
14
16
0L
0H
0F
0D
09
1K
1G
1E
07
b10 !
b10 '
b10 -
18
1;
1"
